fastglmpca/__init__.py
fastglmpca/utils.py
fastglmpca-0.1.1.dist-info/licenses/LICENSE
fastglmpca-0.1.1.dist-info/METADATA
fastglmpca-0.1.1.dist-info/WHEEL
fastglmpca-0.1.1.dist-info/top_level.txt
fastglmpca-0.1.1.dist-info/RECORD
