Metadata-Version: 2.4
Name: fastglmpca
Version: 0.1.1
Summary: Python implementation of fastglmpca [Weine et al., Bioinformatics, 2024] algorithm with PyTorch
Home-page: https://github.com/serjisa/py-fastglmpca
Author: Sergey Isaev
Author-email: s@isaev.cc
Classifier: Programming Language :: Python :: 3
Classifier: License :: OSI Approved :: MIT License
Classifier: Operating System :: OS Independent
Requires-Python: >=3.8
License-File: LICENSE
Requires-Dist: numpy
Requires-Dist: torch
Requires-Dist: scipy
Requires-Dist: tqdm
Dynamic: license-file
